{
  "frames": [
    {
      "frame": {
        "anchor_center": {
          "x": 4,
          "y": 16
        },
        "anchor_center_world": {
          "x": 4,
          "y": 16
        },
        "displayName": "dummy_arm_back",
        "filenameStem": "dummy_arm_back",
        "has_own_ambient_light": false,
        "id": {
          "frameIndex": 0,
          "group": 0
        },
        "size": {
          "height": 32,
          "width": 8
        },
        "world_size": {
          "height": 32,
          "width": 8
        }
      },
      "frame_coordinates": {
        "bottom": 160,
        "left": 128
      },
      "texture_coordinates": {
        "anchorCenterX": 0.517578125,
        "anchorCenterY": 0.689453125,
        "bottom": 0.626953125,
        "left": 0.501953125,
        "right": 0.529296875,
        "top": 0.748046875
      },
      "texture_space_size": {
        "height": 0.125,
        "width": 0.03125
      }
    },
    {
      "frame": {
        "anchor_center": {
          "x": 4,
          "y": 16
        },
        "anchor_center_world": {
          "x": 4,
          "y": 16
        },
        "displayName": "dummy_arm_front",
        "filenameStem": "dummy_arm_front",
        "has_own_ambient_light": false,
        "id": {
          "frameIndex": 1,
          "group": 0
        },
        "size": {
          "height": 32,
          "width": 8
        },
        "world_size": {
          "height": 32,
          "width": 8
        }
      },
      "frame_coordinates": {
        "bottom": 160,
        "left": 64
      },
      "texture_coordinates": {
        "anchorCenterX": 0.267578125,
        "anchorCenterY": 0.689453125,
        "bottom": 0.626953125,
        "left": 0.251953125,
        "right": 0.279296875,
        "top": 0.748046875
      },
      "texture_space_size": {
        "height": 0.125,
        "width": 0.03125
      }
    },
    {
      "frame": {
        "anchor_center": {
          "x": 4,
          "y": 16
        },
        "anchor_center_world": {
          "x": 4,
          "y": 16
        },
        "displayName": "dummy_arm_side",
        "filenameStem": "dummy_arm_side",
        "has_own_ambient_light": false,
        "id": {
          "frameIndex": 2,
          "group": 0
        },
        "size": {
          "height": 32,
          "width": 8
        },
        "world_size": {
          "height": 32,
          "width": 8
        }
      },
      "frame_coordinates": {
        "bottom": 160,
        "left": 72
      },
      "texture_coordinates": {
        "anchorCenterX": 0.298828125,
        "anchorCenterY": 0.689453125,
        "bottom": 0.626953125,
        "left": 0.283203125,
        "right": 0.310546875,
        "top": 0.748046875
      },
      "texture_space_size": {
        "height": 0.125,
        "width": 0.03125
      }
    },
    {
      "frame": {
        "anchor_center": {
          "x": 8,
          "y": 8
        },
        "anchor_center_world": {
          "x": 8,
          "y": 8
        },
        "displayName": "dummy_head_back",
        "filenameStem": "dummy_head_back",
        "has_own_ambient_light": false,
        "id": {
          "frameIndex": 3,
          "group": 0
        },
        "size": {
          "height": 16,
          "width": 16
        },
        "world_size": {
          "height": 16,
          "width": 16
        }
      },
      "frame_coordinates": {
        "bottom": 160,
        "left": 232
      },
      "texture_coordinates": {
        "anchorCenterX": 0.939453125,
        "anchorCenterY": 0.658203125,
        "bottom": 0.626953125,
        "left": 0.908203125,
        "right": 0.966796875,
        "top": 0.685546875
      },
      "texture_space_size": {
        "height": 0.0625,
        "width": 0.0625
      }
    },
    {
      "frame": {
        "anchor_center": {
          "x": 8,
          "y": 8
        },
        "anchor_center_world": {
          "x": 8,
          "y": 8
        },
        "displayName": "dummy_head_front",
        "filenameStem": "dummy_head_front",
        "has_own_ambient_light": false,
        "id": {
          "frameIndex": 4,
          "group": 0
        },
        "size": {
          "height": 16,
          "width": 16
        },
        "world_size": {
          "height": 16,
          "width": 16
        }
      },
      "frame_coordinates": {
        "bottom": 176,
        "left": 136
      },
      "texture_coordinates": {
        "anchorCenterX": 0.564453125,
        "anchorCenterY": 0.720703125,
        "bottom": 0.689453125,
        "left": 0.533203125,
        "right": 0.591796875,
        "top": 0.748046875
      },
      "texture_space_size": {
        "height": 0.0625,
        "width": 0.0625
      }
    },
    {
      "frame": {
        "anchor_center": {
          "x": 8,
          "y": 8
        },
        "anchor_center_world": {
          "x": 8,
          "y": 8
        },
        "displayName": "dummy_head_side",
        "filenameStem": "dummy_head_side",
        "has_own_ambient_light": false,
        "id": {
          "frameIndex": 5,
          "group": 0
        },
        "size": {
          "height": 16,
          "width": 16
        },
        "world_size": {
          "height": 16,
          "width": 16
        }
      },
      "frame_coordinates": {
        "bottom": 176,
        "left": 152
      },
      "texture_coordinates": {
        "anchorCenterX": 0.626953125,
        "anchorCenterY": 0.720703125,
        "bottom": 0.689453125,
        "left": 0.595703125,
        "right": 0.654296875,
        "top": 0.748046875
      },
      "texture_space_size": {
        "height": 0.0625,
        "width": 0.0625
      }
    },
    {
      "frame": {
        "anchor_center": {
          "x": 8,
          "y": 16
        },
        "anchor_center_world": {
          "x": 8,
          "y": 16
        },
        "displayName": "dummy_leg_back",
        "filenameStem": "dummy_leg_back",
        "has_own_ambient_light": false,
        "id": {
          "frameIndex": 6,
          "group": 0
        },
        "size": {
          "height": 32,
          "width": 16
        },
        "world_size": {
          "height": 32,
          "width": 16
        }
      },
      "frame_coordinates": {
        "bottom": 128,
        "left": 128
      },
      "texture_coordinates": {
        "anchorCenterX": 0.533203125,
        "anchorCenterY": 0.564453125,
        "bottom": 0.501953125,
        "left": 0.501953125,
        "right": 0.560546875,
        "top": 0.623046875
      },
      "texture_space_size": {
        "height": 0.125,
        "width": 0.0625
      }
    },
    {
      "frame": {
        "anchor_center": {
          "x": 8,
          "y": 16
        },
        "anchor_center_world": {
          "x": 8,
          "y": 16
        },
        "displayName": "dummy_leg_front",
        "filenameStem": "dummy_leg_front",
        "has_own_ambient_light": false,
        "id": {
          "frameIndex": 7,
          "group": 0
        },
        "size": {
          "height": 32,
          "width": 16
        },
        "world_size": {
          "height": 32,
          "width": 16
        }
      },
      "frame_coordinates": {
        "bottom": 128,
        "left": 144
      },
      "texture_coordinates": {
        "anchorCenterX": 0.595703125,
        "anchorCenterY": 0.564453125,
        "bottom": 0.501953125,
        "left": 0.564453125,
        "right": 0.623046875,
        "top": 0.623046875
      },
      "texture_space_size": {
        "height": 0.125,
        "width": 0.0625
      }
    },
    {
      "frame": {
        "anchor_center": {
          "x": 8,
          "y": 16
        },
        "anchor_center_world": {
          "x": 8,
          "y": 16
        },
        "displayName": "dummy_leg_side",
        "filenameStem": "dummy_leg_side",
        "has_own_ambient_light": false,
        "id": {
          "frameIndex": 8,
          "group": 0
        },
        "size": {
          "height": 32,
          "width": 16
        },
        "world_size": {
          "height": 32,
          "width": 16
        }
      },
      "frame_coordinates": {
        "bottom": 128,
        "left": 160
      },
      "texture_coordinates": {
        "anchorCenterX": 0.658203125,
        "anchorCenterY": 0.564453125,
        "bottom": 0.501953125,
        "left": 0.626953125,
        "right": 0.685546875,
        "top": 0.623046875
      },
      "texture_space_size": {
        "height": 0.125,
        "width": 0.0625
      }
    },
    {
      "frame": {
        "anchor_center": {
          "x": 11,
          "y": 16
        },
        "anchor_center_world": {
          "x": 11,
          "y": 16
        },
        "displayName": "dummy_torso_back",
        "filenameStem": "dummy_torso_back",
        "has_own_ambient_light": false,
        "id": {
          "frameIndex": 9,
          "group": 0
        },
        "size": {
          "height": 32,
          "width": 22
        },
        "world_size": {
          "height": 32,
          "width": 22
        }
      },
      "frame_coordinates": {
        "bottom": 128,
        "left": 69
      },
      "texture_coordinates": {
        "anchorCenterX": 0.314453125,
        "anchorCenterY": 0.564453125,
        "bottom": 0.501953125,
        "left": 0.271484375,
        "right": 0.353515625,
        "top": 0.623046875
      },
      "texture_space_size": {
        "height": 0.125,
        "width": 0.0859375
      }
    },
    {
      "frame": {
        "anchor_center": {
          "x": 11,
          "y": 16
        },
        "anchor_center_world": {
          "x": 11,
          "y": 16
        },
        "displayName": "dummy_torso_front",
        "filenameStem": "dummy_torso_front",
        "has_own_ambient_light": false,
        "id": {
          "frameIndex": 10,
          "group": 0
        },
        "size": {
          "height": 32,
          "width": 22
        },
        "world_size": {
          "height": 32,
          "width": 22
        }
      },
      "frame_coordinates": {
        "bottom": 128,
        "left": 101
      },
      "texture_coordinates": {
        "anchorCenterX": 0.439453125,
        "anchorCenterY": 0.564453125,
        "bottom": 0.501953125,
        "left": 0.396484375,
        "right": 0.478515625,
        "top": 0.623046875
      },
      "texture_space_size": {
        "height": 0.125,
        "width": 0.0859375
      }
    },
    {
      "frame": {
        "anchor_center": {
          "x": 11,
          "y": 16
        },
        "anchor_center_world": {
          "x": 11,
          "y": 16
        },
        "displayName": "dummy_torso_side",
        "filenameStem": "dummy_torso_side",
        "has_own_ambient_light": false,
        "id": {
          "frameIndex": 11,
          "group": 0
        },
        "size": {
          "height": 32,
          "width": 22
        },
        "world_size": {
          "height": 32,
          "width": 22
        }
      },
      "frame_coordinates": {
        "bottom": 64,
        "left": 197
      },
      "texture_coordinates": {
        "anchorCenterX": 0.814453125,
        "anchorCenterY": 0.314453125,
        "bottom": 0.251953125,
        "left": 0.771484375,
        "right": 0.853515625,
        "top": 0.373046875
      },
      "texture_space_size": {
        "height": 0.125,
        "width": 0.0859375
      }
    },
    {
      "frame": {
        "anchor_center": {
          "x": 4,
          "y": 16
        },
        "anchor_center_world": {
          "x": 4,
          "y": 16
        },
        "displayName": "female_civilian_passenger_1_arm_back",
        "filenameStem": "female_civilian_passenger_1_arm_back",
        "has_own_ambient_light": false,
        "id": {
          "frameIndex": 12,
          "group": 0
        },
        "size": {
          "height": 32,
          "width": 8
        },
        "world_size": {
          "height": 32,
          "width": 8
        }
      },
      "frame_coordinates": {
        "bottom": 160,
        "left": 80
      },
      "texture_coordinates": {
        "anchorCenterX": 0.330078125,
        "anchorCenterY": 0.689453125,
        "bottom": 0.626953125,
        "left": 0.314453125,
        "right": 0.341796875,
        "top": 0.748046875
      },
      "texture_space_size": {
        "height": 0.125,
        "width": 0.03125
      }
    },
    {
      "frame": {
        "anchor_center": {
          "x": 4,
          "y": 16
        },
        "anchor_center_world": {
          "x": 4,
          "y": 16
        },
        "displayName": "female_civilian_passenger_1_arm_front",
        "filenameStem": "female_civilian_passenger_1_arm_front",
        "has_own_ambient_light": false,
        "id": {
          "frameIndex": 13,
          "group": 0
        },
        "size": {
          "height": 32,
          "width": 8
        },
        "world_size": {
          "height": 32,
          "width": 8
        }
      },
      "frame_coordinates": {
        "bottom": 160,
        "left": 88
      },
      "texture_coordinates": {
        "anchorCenterX": 0.361328125,
        "anchorCenterY": 0.689453125,
        "bottom": 0.626953125,
        "left": 0.345703125,
        "right": 0.373046875,
        "top": 0.748046875
      },
      "texture_space_size": {
        "height": 0.125,
        "width": 0.03125
      }
    },
    {
      "frame": {
        "anchor_center": {
          "x": 4,
          "y": 16
        },
        "anchor_center_world": {
          "x": 4,
          "y": 16
        },
        "displayName": "female_civilian_passenger_1_arm_side",
        "filenameStem": "female_civilian_passenger_1_arm_side",
        "has_own_ambient_light": false,
        "id": {
          "frameIndex": 14,
          "group": 0
        },
        "size": {
          "height": 32,
          "width": 8
        },
        "world_size": {
          "height": 32,
          "width": 8
        }
      },
      "frame_coordinates": {
        "bottom": 160,
        "left": 96
      },
      "texture_coordinates": {
        "anchorCenterX": 0.392578125,
        "anchorCenterY": 0.689453125,
        "bottom": 0.626953125,
        "left": 0.376953125,
        "right": 0.404296875,
        "top": 0.748046875
      },
      "texture_space_size": {
        "height": 0.125,
        "width": 0.03125
      }
    },
    {
      "frame": {
        "anchor_center": {
          "x": 8,
          "y": 10
        },
        "anchor_center_world": {
          "x": 8,
          "y": 10
        },
        "displayName": "female_civilian_passenger_1_head_back",
        "filenameStem": "female_civilian_passenger_1_head_back",
        "has_own_ambient_light": false,
        "id": {
          "frameIndex": 15,
          "group": 0
        },
        "size": {
          "height": 20,
          "width": 16
        },
        "world_size": {
          "height": 20,
          "width": 16
        }
      },
      "frame_coordinates": {
        "bottom": 134,
        "left": 176
      },
      "texture_coordinates": {
        "anchorCenterX": 0.720703125,
        "anchorCenterY": 0.564453125,
        "bottom": 0.525390625,
        "left": 0.689453125,
        "right": 0.748046875,
        "top": 0.599609375
      },
      "texture_space_size": {
        "height": 0.078125,
        "width": 0.0625
      }
    },
    {
      "frame": {
        "anchor_center": {
          "x": 8,
          "y": 10
        },
        "anchor_center_world": {
          "x": 8,
          "y": 10
        },
        "displayName": "female_civilian_passenger_1_head_front",
        "filenameStem": "female_civilian_passenger_1_head_front",
        "has_own_ambient_light": false,
        "id": {
          "frameIndex": 16,
          "group": 0
        },
        "size": {
          "height": 20,
          "width": 16
        },
        "world_size": {
          "height": 20,
          "width": 16
        }
      },
      "frame_coordinates": {
        "bottom": 134,
        "left": 192
      },
      "texture_coordinates": {
        "anchorCenterX": 0.783203125,
        "anchorCenterY": 0.564453125,
        "bottom": 0.525390625,
        "left": 0.751953125,
        "right": 0.810546875,
        "top": 0.599609375
      },
      "texture_space_size": {
        "height": 0.078125,
        "width": 0.0625
      }
    },
    {
      "frame": {
        "anchor_center": {
          "x": 8,
          "y": 10
        },
        "anchor_center_world": {
          "x": 8,
          "y": 10
        },
        "displayName": "female_civilian_passenger_1_head_side",
        "filenameStem": "female_civilian_passenger_1_head_side",
        "has_own_ambient_light": false,
        "id": {
          "frameIndex": 17,
          "group": 0
        },
        "size": {
          "height": 20,
          "width": 16
        },
        "world_size": {
          "height": 20,
          "width": 16
        }
      },
      "frame_coordinates": {
        "bottom": 134,
        "left": 224
      },
      "texture_coordinates": {
        "anchorCenterX": 0.908203125,
        "anchorCenterY": 0.564453125,
        "bottom": 0.525390625,
        "left": 0.876953125,
        "right": 0.935546875,
        "top": 0.599609375
      },
      "texture_space_size": {
        "height": 0.078125,
        "width": 0.0625
      }
    },
    {
      "frame": {
        "anchor_center": {
          "x": 8,
          "y": 16
        },
        "anchor_center_world": {
          "x": 8,
          "y": 16
        },
        "displayName": "female_civilian_passenger_1_leg_back",
        "filenameStem": "female_civilian_passenger_1_leg_back",
        "has_own_ambient_light": false,
        "id": {
          "frameIndex": 18,
          "group": 0
        },
        "size": {
          "height": 32,
          "width": 16
        },
        "world_size": {
          "height": 32,
          "width": 16
        }
      },
      "frame_coordinates": {
        "bottom": 160,
        "left": 48
      },
      "texture_coordinates": {
        "anchorCenterX": 0.220703125,
        "anchorCenterY": 0.689453125,
        "bottom": 0.626953125,
        "left": 0.189453125,
        "right": 0.248046875,
        "top": 0.748046875
      },
      "texture_space_size": {
        "height": 0.125,
        "width": 0.0625
      }
    },
    {
      "frame": {
        "anchor_center": {
          "x": 8,
          "y": 16
        },
        "anchor_center_world": {
          "x": 8,
          "y": 16
        },
        "displayName": "female_civilian_passenger_1_leg_front",
        "filenameStem": "female_civilian_passenger_1_leg_front",
        "has_own_ambient_light": false,
        "id": {
          "frameIndex": 19,
          "group": 0
        },
        "size": {
          "height": 32,
          "width": 16
        },
        "world_size": {
          "height": 32,
          "width": 16
        }
      },
      "frame_coordinates": {
        "bottom": 128,
        "left": 208
      },
      "texture_coordinates": {
        "anchorCenterX": 0.845703125,
        "anchorCenterY": 0.564453125,
        "bottom": 0.501953125,
        "left": 0.814453125,
        "right": 0.873046875,
        "top": 0.623046875
      },
      "texture_space_size": {
        "height": 0.125,
        "width": 0.0625
      }
    },
    {
      "frame": {
        "anchor_center": {
          "x": 8,
          "y": 16
        },
        "anchor_center_world": {
          "x": 8,
          "y": 16
        },
        "displayName": "female_civilian_passenger_1_leg_side",
        "filenameStem": "female_civilian_passenger_1_leg_side",
        "has_own_ambient_light": false,
        "id": {
          "frameIndex": 20,
          "group": 0
        },
        "size": {
          "height": 32,
          "width": 16
        },
        "world_size": {
          "height": 32,
          "width": 16
        }
      },
      "frame_coordinates": {
        "bottom": 160,
        "left": 32
      },
      "texture_coordinates": {
        "anchorCenterX": 0.158203125,
        "anchorCenterY": 0.689453125,
        "bottom": 0.626953125,
        "left": 0.126953125,
        "right": 0.185546875,
        "top": 0.748046875
      },
      "texture_space_size": {
        "height": 0.125,
        "width": 0.0625
      }
    },
    {
      "frame": {
        "anchor_center": {
          "x": 13,
          "y": 23
        },
        "anchor_center_world": {
          "x": 13,
          "y": 23
        },
        "displayName": "female_civilian_passenger_1_torso_back",
        "filenameStem": "female_civilian_passenger_1_torso_back",
        "has_own_ambient_light": false,
        "id": {
          "frameIndex": 21,
          "group": 0
        },
        "size": {
          "height": 46,
          "width": 26
        },
        "world_size": {
          "height": 46,
          "width": 26
        }
      },
      "frame_coordinates": {
        "bottom": 73,
        "left": 99
      },
      "texture_coordinates": {
        "anchorCenterX": 0.439453125,
        "anchorCenterY": 0.376953125,
        "bottom": 0.287109375,
        "left": 0.388671875,
        "right": 0.486328125,
        "top": 0.462890625
      },
      "texture_space_size": {
        "height": 0.1796875,
        "width": 0.1015625
      }
    },
    {
      "frame": {
        "anchor_center": {
          "x": 13,
          "y": 23
        },
        "anchor_center_world": {
          "x": 13,
          "y": 23
        },
        "displayName": "female_civilian_passenger_1_torso_front",
        "filenameStem": "female_civilian_passenger_1_torso_front",
        "has_own_ambient_light": false,
        "id": {
          "frameIndex": 22,
          "group": 0
        },
        "size": {
          "height": 46,
          "width": 26
        },
        "world_size": {
          "height": 46,
          "width": 26
        }
      },
      "frame_coordinates": {
        "bottom": 9,
        "left": 67
      },
      "texture_coordinates": {
        "anchorCenterX": 0.314453125,
        "anchorCenterY": 0.126953125,
        "bottom": 0.037109375,
        "left": 0.263671875,
        "right": 0.361328125,
        "top": 0.212890625
      },
      "texture_space_size": {
        "height": 0.1796875,
        "width": 0.1015625
      }
    },
    {
      "frame": {
        "anchor_center": {
          "x": 13,
          "y": 23
        },
        "anchor_center_world": {
          "x": 13,
          "y": 23
        },
        "displayName": "female_civilian_passenger_1_torso_side",
        "filenameStem": "female_civilian_passenger_1_torso_side",
        "has_own_ambient_light": false,
        "id": {
          "frameIndex": 23,
          "group": 0
        },
        "size": {
          "height": 46,
          "width": 26
        },
        "world_size": {
          "height": 46,
          "width": 26
        }
      },
      "frame_coordinates": {
        "bottom": 9,
        "left": 99
      },
      "texture_coordinates": {
        "anchorCenterX": 0.439453125,
        "anchorCenterY": 0.126953125,
        "bottom": 0.037109375,
        "left": 0.388671875,
        "right": 0.486328125,
        "top": 0.212890625
      },
      "texture_space_size": {
        "height": 0.1796875,
        "width": 0.1015625
      }
    },
    {
      "frame": {
        "anchor_center": {
          "x": 16,
          "y": 17
        },
        "anchor_center_world": {
          "x": 16,
          "y": 17
        },
        "displayName": "barrel_1",
        "filenameStem": "barrel_1",
        "has_own_ambient_light": false,
        "id": {
          "frameIndex": 24,
          "group": 0
        },
        "size": {
          "height": 34,
          "width": 32
        },
        "world_size": {
          "height": 34,
          "width": 32
        }
      },
      "frame_coordinates": {
        "bottom": 79,
        "left": 0
      },
      "texture_coordinates": {
        "anchorCenterX": 0.064453125,
        "anchorCenterY": 0.376953125,
        "bottom": 0.310546875,
        "left": 0.001953125,
        "right": 0.123046875,
        "top": 0.439453125
      },
      "texture_space_size": {
        "height": 0.1328125,
        "width": 0.125
      }
    },
    {
      "frame": {
        "anchor_center": {
          "x": 28,
          "y": 20
        },
        "anchor_center_world": {
          "x": 28,
          "y": 20
        },
        "displayName": "cabin_desk_1",
        "filenameStem": "cabin_desk_1",
        "has_own_ambient_light": false,
        "id": {
          "frameIndex": 25,
          "group": 0
        },
        "size": {
          "height": 40,
          "width": 56
        },
        "world_size": {
          "height": 40,
          "width": 56
        }
      },
      "frame_coordinates": {
        "bottom": 12,
        "left": 4
      },
      "texture_coordinates": {
        "anchorCenterX": 0.126953125,
        "anchorCenterY": 0.126953125,
        "bottom": 0.048828125,
        "left": 0.017578125,
        "right": 0.232421875,
        "top": 0.201171875
      },
      "texture_space_size": {
        "height": 0.15625,
        "width": 0.21875
      }
    },
    {
      "frame": {
        "anchor_center": {
          "x": 11,
          "y": 8
        },
        "anchor_center_world": {
          "x": 11,
          "y": 8
        },
        "displayName": "chest_1",
        "filenameStem": "chest_1",
        "has_own_ambient_light": false,
        "id": {
          "frameIndex": 26,
          "group": 0
        },
        "size": {
          "height": 16,
          "width": 22
        },
        "world_size": {
          "height": 16,
          "width": 22
        }
      },
      "frame_coordinates": {
        "bottom": 160,
        "left": 141
      },
      "texture_coordinates": {
        "anchorCenterX": 0.595703125,
        "anchorCenterY": 0.658203125,
        "bottom": 0.626953125,
        "left": 0.552734375,
        "right": 0.634765625,
        "top": 0.685546875
      },
      "texture_space_size": {
        "height": 0.0625,
        "width": 0.0859375
      }
    },
    {
      "frame": {
        "anchor_center": {
          "x": 11,
          "y": 8
        },
        "anchor_center_world": {
          "x": 11,
          "y": 8
        },
        "displayName": "chest_2",
        "filenameStem": "chest_2",
        "has_own_ambient_light": false,
        "id": {
          "frameIndex": 27,
          "group": 0
        },
        "size": {
          "height": 16,
          "width": 22
        },
        "world_size": {
          "height": 16,
          "width": 22
        }
      },
      "frame_coordinates": {
        "bottom": 160,
        "left": 173
      },
      "texture_coordinates": {
        "anchorCenterX": 0.720703125,
        "anchorCenterY": 0.658203125,
        "bottom": 0.626953125,
        "left": 0.677734375,
        "right": 0.759765625,
        "top": 0.685546875
      },
      "texture_space_size": {
        "height": 0.0625,
        "width": 0.0859375
      }
    },
    {
      "frame": {
        "anchor_center": {
          "x": 11,
          "y": 8
        },
        "anchor_center_world": {
          "x": 11,
          "y": 8
        },
        "displayName": "chest_3",
        "filenameStem": "chest_3",
        "has_own_ambient_light": false,
        "id": {
          "frameIndex": 28,
          "group": 0
        },
        "size": {
          "height": 16,
          "width": 22
        },
        "world_size": {
          "height": 16,
          "width": 22
        }
      },
      "frame_coordinates": {
        "bottom": 160,
        "left": 205
      },
      "texture_coordinates": {
        "anchorCenterX": 0.845703125,
        "anchorCenterY": 0.658203125,
        "bottom": 0.626953125,
        "left": 0.802734375,
        "right": 0.884765625,
        "top": 0.685546875
      },
      "texture_space_size": {
        "height": 0.0625,
        "width": 0.0859375
      }
    },
    {
      "frame": {
        "anchor_center": {
          "x": 16,
          "y": 16
        },
        "anchor_center_world": {
          "x": 16,
          "y": 16
        },
        "displayName": "crate_1",
        "filenameStem": "crate_1",
        "has_own_ambient_light": false,
        "id": {
          "frameIndex": 29,
          "group": 0
        },
        "size": {
          "height": 32,
          "width": 32
        },
        "world_size": {
          "height": 32,
          "width": 32
        }
      },
      "frame_coordinates": {
        "bottom": 128,
        "left": 32
      },
      "texture_coordinates": {
        "anchorCenterX": 0.189453125,
        "anchorCenterY": 0.564453125,
        "bottom": 0.501953125,
        "left": 0.126953125,
        "right": 0.248046875,
        "top": 0.623046875
      },
      "texture_space_size": {
        "height": 0.125,
        "width": 0.125
      }
    },
    {
      "frame": {
        "anchor_center": {
          "x": 13,
          "y": 17
        },
        "anchor_center_world": {
          "x": 13,
          "y": 17
        },
        "displayName": "drum_1",
        "filenameStem": "drum_1",
        "has_own_ambient_light": false,
        "id": {
          "frameIndex": 30,
          "group": 0
        },
        "size": {
          "height": 34,
          "width": 26
        },
        "world_size": {
          "height": 34,
          "width": 26
        }
      },
      "frame_coordinates": {
        "bottom": 79,
        "left": 67
      },
      "texture_coordinates": {
        "anchorCenterX": 0.314453125,
        "anchorCenterY": 0.376953125,
        "bottom": 0.310546875,
        "left": 0.263671875,
        "right": 0.361328125,
        "top": 0.439453125
      },
      "texture_space_size": {
        "height": 0.1328125,
        "width": 0.1015625
      }
    },
    {
      "frame": {
        "anchor_center": {
          "x": 13,
          "y": 17
        },
        "anchor_center_world": {
          "x": 13,
          "y": 17
        },
        "displayName": "drum_2",
        "filenameStem": "drum_2",
        "has_own_ambient_light": false,
        "id": {
          "frameIndex": 31,
          "group": 0
        },
        "size": {
          "height": 34,
          "width": 26
        },
        "world_size": {
          "height": 34,
          "width": 26
        }
      },
      "frame_coordinates": {
        "bottom": 79,
        "left": 35
      },
      "texture_coordinates": {
        "anchorCenterX": 0.189453125,
        "anchorCenterY": 0.376953125,
        "bottom": 0.310546875,
        "left": 0.138671875,
        "right": 0.236328125,
        "top": 0.439453125
      },
      "texture_space_size": {
        "height": 0.1328125,
        "width": 0.1015625
      }
    },
    {
      "frame": {
        "anchor_center": {
          "x": 16,
          "y": 16
        },
        "anchor_center_world": {
          "x": 16,
          "y": 16
        },
        "displayName": "particle_1",
        "filenameStem": "particle_1",
        "has_own_ambient_light": false,
        "id": {
          "frameIndex": 32,
          "group": 0
        },
        "size": {
          "height": 32,
          "width": 32
        },
        "world_size": {
          "height": 32,
          "width": 32
        }
      },
      "frame_coordinates": {
        "bottom": 64,
        "left": 224
      },
      "texture_coordinates": {
        "anchorCenterX": 0.939453125,
        "anchorCenterY": 0.314453125,
        "bottom": 0.251953125,
        "left": 0.876953125,
        "right": 0.998046875,
        "top": 0.373046875
      },
      "texture_space_size": {
        "height": 0.125,
        "width": 0.125
      }
    },
    {
      "frame": {
        "anchor_center": {
          "x": 25,
          "y": 16
        },
        "anchor_center_world": {
          "x": 25,
          "y": 16
        },
        "displayName": "piano_1",
        "filenameStem": "piano_1",
        "has_own_ambient_light": false,
        "id": {
          "frameIndex": 33,
          "group": 0
        },
        "size": {
          "height": 32,
          "width": 50
        },
        "world_size": {
          "height": 32,
          "width": 50
        }
      },
      "frame_coordinates": {
        "bottom": 64,
        "left": 135
      },
      "texture_coordinates": {
        "anchorCenterX": 0.626953125,
        "anchorCenterY": 0.314453125,
        "bottom": 0.251953125,
        "left": 0.529296875,
        "right": 0.720703125,
        "top": 0.373046875
      },
      "texture_space_size": {
        "height": 0.125,
        "width": 0.1953125
      }
    },
    {
      "frame": {
        "anchor_center": {
          "x": 16,
          "y": 15
        },
        "anchor_center_world": {
          "x": 16,
          "y": 15
        },
        "displayName": "small_table_1",
        "filenameStem": "small_table_1",
        "has_own_ambient_light": false,
        "id": {
          "frameIndex": 34,
          "group": 0
        },
        "size": {
          "height": 30,
          "width": 32
        },
        "world_size": {
          "height": 30,
          "width": 32
        }
      },
      "frame_coordinates": {
        "bottom": 97,
        "left": 128
      },
      "texture_coordinates": {
        "anchorCenterX": 0.564453125,
        "anchorCenterY": 0.439453125,
        "bottom": 0.380859375,
        "left": 0.501953125,
        "right": 0.623046875,
        "top": 0.494140625
      },
      "texture_space_size": {
        "height": 0.1171875,
        "width": 0.125
      }
    },
    {
      "frame": {
        "anchor_center": {
          "x": 16,
          "y": 15
        },
        "anchor_center_world": {
          "x": 16,
          "y": 16
        },
        "displayName": "small_table_2",
        "filenameStem": "small_table_2",
        "has_own_ambient_light": false,
        "id": {
          "frameIndex": 35,
          "group": 0
        },
        "size": {
          "height": 31,
          "width": 32
        },
        "world_size": {
          "height": 31,
          "width": 32
        }
      },
      "frame_coordinates": {
        "bottom": 96,
        "left": 160
      },
      "texture_coordinates": {
        "anchorCenterX": 0.689453125,
        "anchorCenterY": 0.435546875,
        "bottom": 0.376953125,
        "left": 0.626953125,
        "right": 0.748046875,
        "top": 0.494140625
      },
      "texture_space_size": {
        "height": 0.12109375,
        "width": 0.125
      }
    },
    {
      "frame": {
        "anchor_center": {
          "x": 4,
          "y": 16
        },
        "anchor_center_world": {
          "x": 4,
          "y": 16
        },
        "displayName": "male_civ_1_arm_back",
        "filenameStem": "male_civ_1_arm_back",
        "has_own_ambient_light": false,
        "id": {
          "frameIndex": 36,
          "group": 0
        },
        "size": {
          "height": 32,
          "width": 8
        },
        "world_size": {
          "height": 32,
          "width": 8
        }
      },
      "frame_coordinates": {
        "bottom": 160,
        "left": 104
      },
      "texture_coordinates": {
        "anchorCenterX": 0.423828125,
        "anchorCenterY": 0.689453125,
        "bottom": 0.626953125,
        "left": 0.408203125,
        "right": 0.435546875,
        "top": 0.748046875
      },
      "texture_space_size": {
        "height": 0.125,
        "width": 0.03125
      }
    },
    {
      "frame": {
        "anchor_center": {
          "x": 4,
          "y": 16
        },
        "anchor_center_world": {
          "x": 4,
          "y": 16
        },
        "displayName": "male_civ_1_arm_front",
        "filenameStem": "male_civ_1_arm_front",
        "has_own_ambient_light": false,
        "id": {
          "frameIndex": 37,
          "group": 0
        },
        "size": {
          "height": 32,
          "width": 8
        },
        "world_size": {
          "height": 32,
          "width": 8
        }
      },
      "frame_coordinates": {
        "bottom": 160,
        "left": 112
      },
      "texture_coordinates": {
        "anchorCenterX": 0.455078125,
        "anchorCenterY": 0.689453125,
        "bottom": 0.626953125,
        "left": 0.439453125,
        "right": 0.466796875,
        "top": 0.748046875
      },
      "texture_space_size": {
        "height": 0.125,
        "width": 0.03125
      }
    },
    {
      "frame": {
        "anchor_center": {
          "x": 4,
          "y": 16
        },
        "anchor_center_world": {
          "x": 4,
          "y": 16
        },
        "displayName": "male_civ_1_arm_side",
        "filenameStem": "male_civ_1_arm_side",
        "has_own_ambient_light": false,
        "id": {
          "frameIndex": 38,
          "group": 0
        },
        "size": {
          "height": 32,
          "width": 8
        },
        "world_size": {
          "height": 32,
          "width": 8
        }
      },
      "frame_coordinates": {
        "bottom": 160,
        "left": 120
      },
      "texture_coordinates": {
        "anchorCenterX": 0.486328125,
        "anchorCenterY": 0.689453125,
        "bottom": 0.626953125,
        "left": 0.470703125,
        "right": 0.498046875,
        "top": 0.748046875
      },
      "texture_space_size": {
        "height": 0.125,
        "width": 0.03125
      }
    },
    {
      "frame": {
        "anchor_center": {
          "x": 8,
          "y": 8
        },
        "anchor_center_world": {
          "x": 8,
          "y": 8
        },
        "displayName": "male_civ_1_head_back",
        "filenameStem": "male_civ_1_head_back",
        "has_own_ambient_light": false,
        "id": {
          "frameIndex": 39,
          "group": 0
        },
        "size": {
          "height": 16,
          "width": 16
        },
        "world_size": {
          "height": 16,
          "width": 16
        }
      },
      "frame_coordinates": {
        "bottom": 176,
        "left": 168
      },
      "texture_coordinates": {
        "anchorCenterX": 0.689453125,
        "anchorCenterY": 0.720703125,
        "bottom": 0.689453125,
        "left": 0.658203125,
        "right": 0.716796875,
        "top": 0.748046875
      },
      "texture_space_size": {
        "height": 0.0625,
        "width": 0.0625
      }
    },
    {
      "frame": {
        "anchor_center": {
          "x": 8,
          "y": 8
        },
        "anchor_center_world": {
          "x": 8,
          "y": 8
        },
        "displayName": "male_civ_1_head_front",
        "filenameStem": "male_civ_1_head_front",
        "has_own_ambient_light": false,
        "id": {
          "frameIndex": 40,
          "group": 0
        },
        "size": {
          "height": 16,
          "width": 16
        },
        "world_size": {
          "height": 16,
          "width": 16
        }
      },
      "frame_coordinates": {
        "bottom": 176,
        "left": 184
      },
      "texture_coordinates": {
        "anchorCenterX": 0.751953125,
        "anchorCenterY": 0.720703125,
        "bottom": 0.689453125,
        "left": 0.720703125,
        "right": 0.779296875,
        "top": 0.748046875
      },
      "texture_space_size": {
        "height": 0.0625,
        "width": 0.0625
      }
    },
    {
      "frame": {
        "anchor_center": {
          "x": 8,
          "y": 8
        },
        "anchor_center_world": {
          "x": 8,
          "y": 8
        },
        "displayName": "male_civ_1_head_side",
        "filenameStem": "male_civ_1_head_side",
        "has_own_ambient_light": false,
        "id": {
          "frameIndex": 41,
          "group": 0
        },
        "size": {
          "height": 16,
          "width": 16
        },
        "world_size": {
          "height": 16,
          "width": 16
        }
      },
      "frame_coordinates": {
        "bottom": 176,
        "left": 200
      },
      "texture_coordinates": {
        "anchorCenterX": 0.814453125,
        "anchorCenterY": 0.720703125,
        "bottom": 0.689453125,
        "left": 0.783203125,
        "right": 0.841796875,
        "top": 0.748046875
      },
      "texture_space_size": {
        "height": 0.0625,
        "width": 0.0625
      }
    },
    {
      "frame": {
        "anchor_center": {
          "x": 8,
          "y": 16
        },
        "anchor_center_world": {
          "x": 8,
          "y": 16
        },
        "displayName": "male_civ_1_leg_back",
        "filenameStem": "male_civ_1_leg_back",
        "has_own_ambient_light": false,
        "id": {
          "frameIndex": 42,
          "group": 0
        },
        "size": {
          "height": 32,
          "width": 16
        },
        "world_size": {
          "height": 32,
          "width": 16
        }
      },
      "frame_coordinates": {
        "bottom": 128,
        "left": 240
      },
      "texture_coordinates": {
        "anchorCenterX": 0.970703125,
        "anchorCenterY": 0.564453125,
        "bottom": 0.501953125,
        "left": 0.939453125,
        "right": 0.998046875,
        "top": 0.623046875
      },
      "texture_space_size": {
        "height": 0.125,
        "width": 0.0625
      }
    },
    {
      "frame": {
        "anchor_center": {
          "x": 8,
          "y": 16
        },
        "anchor_center_world": {
          "x": 8,
          "y": 16
        },
        "displayName": "male_civ_1_leg_front",
        "filenameStem": "male_civ_1_leg_front",
        "has_own_ambient_light": false,
        "id": {
          "frameIndex": 43,
          "group": 0
        },
        "size": {
          "height": 32,
          "width": 16
        },
        "world_size": {
          "height": 32,
          "width": 16
        }
      },
      "frame_coordinates": {
        "bottom": 160,
        "left": 0
      },
      "texture_coordinates": {
        "anchorCenterX": 0.033203125,
        "anchorCenterY": 0.689453125,
        "bottom": 0.626953125,
        "left": 0.001953125,
        "right": 0.060546875,
        "top": 0.748046875
      },
      "texture_space_size": {
        "height": 0.125,
        "width": 0.0625
      }
    },
    {
      "frame": {
        "anchor_center": {
          "x": 8,
          "y": 16
        },
        "anchor_center_world": {
          "x": 8,
          "y": 16
        },
        "displayName": "male_civ_1_leg_side",
        "filenameStem": "male_civ_1_leg_side",
        "has_own_ambient_light": false,
        "id": {
          "frameIndex": 44,
          "group": 0
        },
        "size": {
          "height": 32,
          "width": 16
        },
        "world_size": {
          "height": 32,
          "width": 16
        }
      },
      "frame_coordinates": {
        "bottom": 160,
        "left": 16
      },
      "texture_coordinates": {
        "anchorCenterX": 0.095703125,
        "anchorCenterY": 0.689453125,
        "bottom": 0.626953125,
        "left": 0.064453125,
        "right": 0.123046875,
        "top": 0.748046875
      },
      "texture_space_size": {
        "height": 0.125,
        "width": 0.0625
      }
    },
    {
      "frame": {
        "anchor_center": {
          "x": 11,
          "y": 16
        },
        "anchor_center_world": {
          "x": 11,
          "y": 16
        },
        "displayName": "male_civ_1_torso_back",
        "filenameStem": "male_civ_1_torso_back",
        "has_own_ambient_light": false,
        "id": {
          "frameIndex": 45,
          "group": 0
        },
        "size": {
          "height": 32,
          "width": 22
        },
        "world_size": {
          "height": 32,
          "width": 22
        }
      },
      "frame_coordinates": {
        "bottom": 96,
        "left": 197
      },
      "texture_coordinates": {
        "anchorCenterX": 0.814453125,
        "anchorCenterY": 0.439453125,
        "bottom": 0.376953125,
        "left": 0.771484375,
        "right": 0.853515625,
        "top": 0.498046875
      },
      "texture_space_size": {
        "height": 0.125,
        "width": 0.0859375
      }
    },
    {
      "frame": {
        "anchor_center": {
          "x": 11,
          "y": 16
        },
        "anchor_center_world": {
          "x": 11,
          "y": 16
        },
        "displayName": "male_civ_1_torso_front",
        "filenameStem": "male_civ_1_torso_front",
        "has_own_ambient_light": false,
        "id": {
          "frameIndex": 46,
          "group": 0
        },
        "size": {
          "height": 32,
          "width": 22
        },
        "world_size": {
          "height": 32,
          "width": 22
        }
      },
      "frame_coordinates": {
        "bottom": 96,
        "left": 229
      },
      "texture_coordinates": {
        "anchorCenterX": 0.939453125,
        "anchorCenterY": 0.439453125,
        "bottom": 0.376953125,
        "left": 0.896484375,
        "right": 0.978515625,
        "top": 0.498046875
      },
      "texture_space_size": {
        "height": 0.125,
        "width": 0.0859375
      }
    },
    {
      "frame": {
        "anchor_center": {
          "x": 11,
          "y": 16
        },
        "anchor_center_world": {
          "x": 11,
          "y": 16
        },
        "displayName": "male_civ_1_torso_side",
        "filenameStem": "male_civ_1_torso_side",
        "has_own_ambient_light": false,
        "id": {
          "frameIndex": 47,
          "group": 0
        },
        "size": {
          "height": 32,
          "width": 22
        },
        "world_size": {
          "height": 32,
          "width": 22
        }
      },
      "frame_coordinates": {
        "bottom": 128,
        "left": 5
      },
      "texture_coordinates": {
        "anchorCenterX": 0.064453125,
        "anchorCenterY": 0.564453125,
        "bottom": 0.501953125,
        "left": 0.021484375,
        "right": 0.103515625,
        "top": 0.623046875
      },
      "texture_space_size": {
        "height": 0.125,
        "width": 0.0859375
      }
    }
  ],
  "options": 3,
  "size": {
    "height": 256,
    "width": 256
  }
}
